gamest_plugins/retroachievements/__init__.py
gamest_plugins/retroachievements/module.py
gamest_retroachievements_plugin-0.1.0.dist-info/METADATA
gamest_retroachievements_plugin-0.1.0.dist-info/WHEEL
gamest_retroachievements_plugin-0.1.0.dist-info/top_level.txt
gamest_retroachievements_plugin-0.1.0.dist-info/RECORD
