Metadata-Version: 2.1
Name: gamest-retroachievements-plugin
Version: 0.1.0
Summary: Add status updates from retroachievements to gamest
Home-page: https://github.com/sopoforic/gamest_retroachievements_plugin
Author: Tracy Poff
Author-email: tracy.poff@gmail.com
License: UNKNOWN
Platform: UNKNOWN
Classifier: Development Status :: 4 - Beta
Classifier: Environment :: Win32 (MS Windows)
Classifier: Intended Audience :: End Users/Desktop
Classifier: License :: OSI Approved :: GNU General Public License v3 or later (GPLv3+)
Classifier: Programming Language :: Python :: 3
Classifier: Topic :: Games/Entertainment
Requires-Dist: gamest (<5.0,>=3.0)
Requires-Dist: python-dateutil
Requires-Dist: pytz
Requires-Dist: requests
